<DOMSymbolItem xmlns:xsi="http://www.w3.org/2001/XMLSchema-instance" xmlns="http://ns.adobe.com/xfl/2008/" name="Graphics/Vectors/Symbol 849" itemID="63c25e2b-00000b90" symbolType="graphic" lastModified="1673129643">
  <timeline>
    <DOMTimeline name="Symbol 849">
      <layers>
        <DOMLayer name="Layer 1" color="#4F4FFF" current="true" isSelected="true">
          <frames>
            <DOMFrame index="0" motionTweenScale="false" keyMode="8192">
              <elements>
                <DOMShape isFloating="true">
                  <strokes>
                    <StrokeStyle index="1">
                      <SolidStroke scaleMode="normal" weight="1.05">
                        <fill>
                          <SolidColor color="#313638"/>
                        </fill>
                      </SolidStroke>
                    </StrokeStyle>
                  </strokes>
                  <edges>
                    <Edge strokeStyle="1" edges="!41 98|30 74"/>
                  </edges>
                </DOMShape>
              </elements>
            </DOMFrame>
          </frames>
        </DOMLayer>
        <DOMLayer name="Layer 2" color="#4F4FFF">
          <frames>
            <DOMFrame index="0" motionTweenScale="false" keyMode="8192">
              <elements>
                <DOMShape isFloating="true">
                  <strokes>
                    <StrokeStyle index="1">
                      <SolidStroke scaleMode="normal" weight="1.05">
                        <fill>
                          <SolidColor color="#313638"/>
                        </fill>
                      </SolidStroke>
                    </StrokeStyle>
                  </strokes>
                  <edges>
                    <Edge strokeStyle="1" edges="!41 98|-22 127!-22 127|23 222!23 222|124 175!124 175|110 145!110 145|71 163!71 163|41 98"/>
                  </edges>
                </DOMShape>
              </elements>
            </DOMFrame>
          </frames>
        </DOMLayer>
        <DOMLayer name="Layer 3" color="#4F4FFF">
          <frames>
            <DOMFrame index="0" motionTweenScale="false" keyMode="8192">
              <elements>
                <DOMShape isFloating="true">
                  <strokes>
                    <StrokeStyle index="1">
                      <SolidStroke scaleMode="normal" weight="1.05">
                        <fill>
                          <SolidColor color="#313638"/>
                        </fill>
                      </SolidStroke>
                    </StrokeStyle>
                  </strokes>
                  <edges>
                    <Edge strokeStyle="1" edges="!63 145|34 159"/>
                  </edges>
                </DOMShape>
              </elements>
            </DOMFrame>
          </frames>
        </DOMLayer>
        <DOMLayer name="Layer 4" color="#4F4FFF">
          <frames>
            <DOMFrame index="0" motionTweenScale="false" keyMode="8192">
              <elements>
                <DOMShape isFloating="true">
                  <fills>
                    <FillStyle index="1">
                      <SolidColor color="#6278A6"/>
                    </FillStyle>
                  </fills>
                  <edges>
                    <Edge fillStyle0="1" edges="!22 133|-11 149!-11 149|23 222!23 222|57 206!57 206|22 133"/>
                  </edges>
                </DOMShape>
              </elements>
            </DOMFrame>
          </frames>
        </DOMLayer>
        <DOMLayer name="Layer 5" color="#4F4FFF">
          <frames>
            <DOMFrame index="0" motionTweenScale="false" keyMode="8192">
              <elements>
                <DOMShape isFloating="true">
                  <fills>
                    <FillStyle index="1">
                      <SolidColor color="#596266"/>
                    </FillStyle>
                  </fills>
                  <edges>
                    <Edge fillStyle0="1" edges="!41 98|-22 127!-22 127|23 222!23 222|122 176!122 176|108 146!108 146[90 155 71 163!71 163|41 98"/>
                  </edges>
                </DOMShape>
              </elements>
            </DOMFrame>
          </frames>
        </DOMLayer>
        <DOMLayer name="Layer 6" color="#4F4FFF">
          <frames>
            <DOMFrame index="0" motionTweenScale="false" keyMode="8192">
              <elements>
                <DOMShape isFloating="true">
                  <strokes>
                    <StrokeStyle index="1">
                      <SolidStroke scaleMode="normal" weight="1.05">
                        <fill>
                          <SolidColor color="#1F1F27"/>
                        </fill>
                      </SolidStroke>
                    </StrokeStyle>
                  </strokes>
                  <edges>
                    <Edge strokeStyle="1" edges="!75 253|92 251!92 251[111 247 121 236"/>
                  </edges>
                </DOMShape>
              </elements>
            </DOMFrame>
          </frames>
        </DOMLayer>
        <DOMLayer name="Layer 7" color="#4F4FFF">
          <frames>
            <DOMFrame index="0" motionTweenScale="false" keyMode="8192">
              <elements>
                <DOMShape isFloating="true">
                  <strokes>
                    <StrokeStyle index="1">
                      <SolidStroke scaleMode="normal" weight="1.05">
                        <fill>
                          <SolidColor color="#131318"/>
                        </fill>
                      </SolidStroke>
                    </StrokeStyle>
                  </strokes>
                  <edges>
                    <Edge strokeStyle="1" edges="!72 272|44 237!44 237[21 209 14 185!14 185[47 181 80 166!80 166|106 151!106 151|117 186!117 186[126 220 138 240"/>
                  </edges>
                </DOMShape>
              </elements>
            </DOMFrame>
          </frames>
        </DOMLayer>
        <DOMLayer name="Layer 8" color="#4F4FFF">
          <frames>
            <DOMFrame index="0" motionTweenScale="false" keyMode="8192">
              <elements>
                <DOMShape isFloating="true">
                  <fills>
                    <FillStyle index="1">
                      <SolidColor color="#2B2C37"/>
                    </FillStyle>
                  </fills>
                  <edges>
                    <Edge fillStyle1="1" edges="!138 240|72 272!72 272|44 237!44 237[21 209 14 185!14 185[47 181 80 166!80 166|106 151!106 151|117 186!117 186[126 220 138 240"/>
                  </edges>
                </DOMShape>
              </elements>
            </DOMFrame>
          </frames>
        </DOMLayer>
        <DOMLayer name="Layer 9" color="#4F4FFF">
          <frames>
            <DOMFrame index="0" motionTweenScale="false" keyMode="8192">
              <elements>
                <DOMShape isFloating="true">
                  <strokes>
                    <StrokeStyle index="1">
                      <SolidStroke scaleMode="normal" weight="1.05">
                        <fill>
                          <SolidColor color="#935418"/>
                        </fill>
                      </SolidStroke>
                    </StrokeStyle>
                  </strokes>
                  <edges>
                    <Edge strokeStyle="1" edges="!-47 -4|-41 7!-41 7[-37 21 -43 35"/>
                  </edges>
                </DOMShape>
              </elements>
            </DOMFrame>
          </frames>
        </DOMLayer>
        <DOMLayer name="Layer 10" color="#4F4FFF">
          <frames>
            <DOMFrame index="0" motionTweenScale="false" keyMode="8192">
              <elements>
                <DOMShape isFloating="true">
                  <strokes>
                    <StrokeStyle index="1">
                      <SolidStroke scaleMode="normal" weight="1.05">
                        <fill>
                          <SolidColor color="#604125"/>
                        </fill>
                      </SolidStroke>
                    </StrokeStyle>
                  </strokes>
                  <edges>
                    <Edge strokeStyle="1" edges="!-47 -11|-90 -20!-90 -20[-117 -12 -107 33!-107 33[-96 77 -70 72!-70 72|-36 41"/>
                  </edges>
                </DOMShape>
              </elements>
            </DOMFrame>
          </frames>
        </DOMLayer>
        <DOMLayer name="Layer 11" color="#4F4FFF">
          <frames>
            <DOMFrame index="0" motionTweenScale="false" keyMode="8192">
              <elements>
                <DOMShape isFloating="true">
                  <fills>
                    <FillStyle index="1">
                      <SolidColor color="#B6681E"/>
                    </FillStyle>
                  </fills>
                  <edges>
                    <Edge fillStyle0="1" edges="!-90 -20[-117 -12 -107 33!-107 33[-96 77 -70 72!-70 72|-36 41!-36 41|-47 -11!-47 -11|-90 -20"/>
                  </edges>
                </DOMShape>
              </elements>
            </DOMFrame>
          </frames>
        </DOMLayer>
        <DOMLayer name="Layer 12" color="#4F4FFF">
          <frames>
            <DOMFrame index="0" motionTweenScale="false" keyMode="8192">
              <elements>
                <DOMShape isFloating="true">
                  <fills>
                    <FillStyle index="1">
                      <SolidColor color="#B6681E"/>
                    </FillStyle>
                  </fills>
                  <strokes>
                    <StrokeStyle index="1">
                      <SolidStroke scaleMode="normal" weight="1.05">
                        <fill>
                          <SolidColor color="#604125"/>
                        </fill>
                      </SolidStroke>
                    </StrokeStyle>
                  </strokes>
                  <edges>
                    <Edge fillStyle1="1" strokeStyle="1" edges="!-73 22[-78 2 -86 -12!-86 -12|45 -10!45 -10[40 2 47 17!47 17|53 30!53 30|-70 46!-70 46|-73 22"/>
                  </edges>
                </DOMShape>
              </elements>
            </DOMFrame>
          </frames>
        </DOMLayer>
        <DOMLayer name="Layer 13" color="#4F4FFF">
          <frames>
            <DOMFrame index="0" motionTweenScale="false" keyMode="8192">
              <elements>
                <DOMShape isFloating="true">
                  <strokes>
                    <StrokeStyle index="1">
                      <SolidStroke scaleMode="normal" weight="1.05">
                        <fill>
                          <SolidColor color="#807A6D"/>
                        </fill>
                      </SolidStroke>
                    </StrokeStyle>
                  </strokes>
                  <edges>
                    <Edge strokeStyle="1" edges="!85 212[79 194 55 174!55 174|33 158"/>
                  </edges>
                </DOMShape>
              </elements>
            </DOMFrame>
          </frames>
        </DOMLayer>
        <DOMLayer name="Layer 14" color="#4F4FFF">
          <frames>
            <DOMFrame index="0" motionTweenScale="false" keyMode="8192">
              <elements>
                <DOMShape isFloating="true">
                  <strokes>
                    <StrokeStyle index="1">
                      <SolidStroke scaleMode="normal" weight="1.05">
                        <fill>
                          <SolidColor color="#807A6D"/>
                        </fill>
                      </SolidStroke>
                    </StrokeStyle>
                  </strokes>
                  <edges>
                    <Edge strokeStyle="1" edges="!27 62[4 60 -12 48!-12 48|-23 38"/>
                  </edges>
                </DOMShape>
              </elements>
            </DOMFrame>
          </frames>
        </DOMLayer>
        <DOMLayer name="Layer 15" color="#4F4FFF">
          <frames>
            <DOMFrame index="0" motionTweenScale="false" keyMode="8192">
              <elements>
                <DOMShape isFloating="true">
                  <strokes>
                    <StrokeStyle index="1">
                      <SolidStroke scaleMode="normal" weight="1.05">
                        <fill>
                          <SolidColor color="#565149"/>
                        </fill>
                      </SolidStroke>
                    </StrokeStyle>
                  </strokes>
                  <edges>
                    <Edge strokeStyle="1" edges="!-39 30|-42 48!-42 48[-38 77 10 173!10 173[61 274 76 254!76 254|96 244!96 244|123 223!123 223|90 120!90 120[66 58 41 26!41 26|28 12"/>
                  </edges>
                </DOMShape>
              </elements>
            </DOMFrame>
          </frames>
        </DOMLayer>
        <DOMLayer name="Layer 16" color="#4F4FFF">
          <frames>
            <DOMFrame index="0" motionTweenScale="false" keyMode="8192">
              <elements>
                <DOMShape isFloating="true">
                  <fills>
                    <FillStyle index="1">
                      <SolidColor color="#BCB2A1"/>
                    </FillStyle>
                  </fills>
                  <edges>
                    <Edge fillStyle0="1" edges="!28 12|-39 30!-39 30|-42 48!-42 48[-38 77 10 173!10 173[61 274 76 254!76 254|96 244!96 244|123 223!123 223|90 120!90 120[66 58 41 26!41 26|28 12"/>
                  </edges>
                </DOMShape>
              </elements>
            </DOMFrame>
          </frames>
        </DOMLayer>
        <DOMLayer name="Layer 17" color="#4F4FFF">
          <frames>
            <DOMFrame index="0" motionTweenScale="false" keyMode="8192">
              <elements>
                <DOMShape isFloating="true">
                  <fills>
                    <FillStyle index="1">
                      <SolidColor color="#2B2C37"/>
                    </FillStyle>
                  </fills>
                  <strokes>
                    <StrokeStyle index="1">
                      <SolidStroke scaleMode="normal" weight="1.05">
                        <fill>
                          <SolidColor color="#131318"/>
                        </fill>
                      </SolidStroke>
                    </StrokeStyle>
                  </strokes>
                  <edges>
                    <Edge fillStyle0="1" strokeStyle="1" edges="!92 289|88 296!88 296|83 308!83 308[74 335 89 350!89 350|118 363!118 363[131 359 143 339!143 339|153 320!153 320|109 286!109 286|92 289"/>
                  </edges>
                </DOMShape>
              </elements>
            </DOMFrame>
          </frames>
        </DOMLayer>
        <DOMLayer name="Layer 18" color="#4F4FFF">
          <frames>
            <DOMFrame index="0" motionTweenScale="false" keyMode="8192">
              <elements>
                <DOMShape isFloating="true">
                  <strokes>
                    <StrokeStyle index="1">
                      <SolidStroke scaleMode="normal" weight="1.05">
                        <fill>
                          <SolidColor color="#131318"/>
                        </fill>
                      </SolidStroke>
                    </StrokeStyle>
                  </strokes>
                  <edges>
                    <Edge strokeStyle="1" edges="!84 302|76 285!76 285[68 265 72 258!72 258[92 215 126 223!126 223[143 242 152 269!152 269[163 300 153 320"/>
                  </edges>
                </DOMShape>
              </elements>
            </DOMFrame>
          </frames>
        </DOMLayer>
        <DOMLayer name="Layer 19" color="#4F4FFF">
          <frames>
            <DOMFrame index="0" motionTweenScale="false" keyMode="8192">
              <elements>
                <DOMShape isFloating="true">
                  <fills>
                    <FillStyle index="1">
                      <SolidColor color="#2B2C37"/>
                    </FillStyle>
                  </fills>
                  <edges>
                    <Edge fillStyle1="1" edges="!126 223[143 242 152 269!152 269[163 300 153 320!153 320|84 302!84 302|76 285!76 285[68 265 72 258!72 258[92 215 126 223"/>
                  </edges>
                </DOMShape>
              </elements>
            </DOMFrame>
          </frames>
        </DOMLayer>
      </layers>
    </DOMTimeline>
  </timeline>
</DOMSymbolItem>